Makefile
README.txt
TODO.txt
hudson.sh
setup.py
logchart/__init__.py
logchart/logchart.py
logchart.egg-info/PKG-INFO
logchart.egg-info/SOURCES.txt
logchart.egg-info/dependency_links.txt
logchart.egg-info/entry_points.txt
logchart.egg-info/top_level.txt
logchart.egg-info/zip-safe